api_browser/__init__.py
api_browser/openapi.py
api_browser-0.2.0.dist-info/LICENSE
api_browser-0.2.0.dist-info/METADATA
api_browser-0.2.0.dist-info/WHEEL
api_browser-0.2.0.dist-info/entry_points.txt
api_browser-0.2.0.dist-info/top_level.txt
api_browser-0.2.0.dist-info/RECORD
