Metadata-Version: 2.1
Name: api-browser
Version: 0.2.0
Summary: Browse API documentation
Author: Stephen Mizell
License: Apache-2.0
Project-URL: Homepage, https://github.com/smizell/api-browser
Project-URL: Changelog, https://github.com/smizell/api-browser/releases
Project-URL: Issues, https://github.com/smizell/api-browser/issues
Project-URL: CI, https://github.com/smizell/api-browser/actions
Classifier: License :: OSI Approved :: Apache Software License
Requires-Python: >=3.8
License-File: LICENSE
Requires-Dist: click
Requires-Dist: Flask
Requires-Dist: pyyaml
Requires-Dist: tabulate
Requires-Dist: openapi-spec-validator
Provides-Extra: test
Requires-Dist: pytest; extra == "test"
Requires-Dist: syrupy; extra == "test"
